ffmp_conv/__init__.py
ffmp_conv/_utils.py
ffmp_conv/ffmp_conv.py
ffmp_conv-0.1.dist-info/LICENSE
ffmp_conv-0.1.dist-info/METADATA
ffmp_conv-0.1.dist-info/WHEEL
ffmp_conv-0.1.dist-info/top_level.txt
ffmp_conv-0.1.dist-info/RECORD
